taufactor/__init__.py
taufactor/metrics.py
taufactor/taufactor.py
taufactor/utils.py
taufactor-1.2.1.dist-info/licenses/LICENSE
taufactor-1.2.1.dist-info/METADATA
taufactor-1.2.1.dist-info/WHEEL
taufactor-1.2.1.dist-info/top_level.txt
taufactor-1.2.1.dist-info/RECORD
