Metadata-Version: 2.4
Name: taufactor
Version: 1.2.1
Summary: TauFactor is an application for calculating tortuosity factors from tomographic data
Maintainer-email: tldr group <samuel.cooper@imperial.ac.uk>
License: MIT
Classifier: Development Status :: 4 - Beta
Classifier: Intended Audience :: Science/Research
Classifier: Intended Audience :: Manufacturing
Classifier: Topic :: Scientific/Engineering :: Physics
Classifier: Topic :: Scientific/Engineering :: Chemistry
Classifier: Topic :: Scientific/Engineering :: Image Processing
Classifier: License :: OSI Approved :: MIT License
Classifier: Natural Language :: English
Classifier: Environment :: GPU
Classifier: Environment :: GPU :: NVIDIA CUDA
Classifier: Programming Language :: Python :: 3
Classifier: Programming Language :: Python :: 3.9
Classifier: Programming Language :: Python :: 3.10
Classifier: Programming Language :: Python :: 3.11
Classifier: Programming Language :: Python :: 3.12
Requires-Python: >=3.9
License-File: LICENSE
Requires-Dist: numpy>=1.21
Requires-Dist: matplotlib>=3.4
Requires-Dist: pyvista>=0.38
Requires-Dist: tifffile>=2023.2.3
Requires-Dist: scikit-image>=0.20.0
Requires-Dist: scipy>=1.3
Requires-Dist: psutil>=5.9.0
Requires-Dist: ipython>=7.0.0
Requires-Dist: torch>=2.1
Provides-Extra: dev
Requires-Dist: pytest; extra == "dev"
Requires-Dist: ruff; extra == "dev"
Provides-Extra: notebooks
Requires-Dist: ipywidgets; extra == "notebooks"
Requires-Dist: ipympl; extra == "notebooks"
Requires-Dist: notebook; extra == "notebooks"
Dynamic: license-file
